feature_forge/__init__.py
feature_forge/smith.py
feature_forge/evaluators/__init__.py
feature_forge/evaluators/scorer.py
feature_forge/generators/__init__.py
feature_forge/generators/aggregations.py
feature_forge/generators/datetime.py
feature_forge/generators/encoding.py
feature_forge/generators/interactions.py
feature_forge/generators/polynomial.py
feature_forge/selectors/__init__.py
feature_forge/selectors/correlation.py
feature_forge/selectors/importance.py
feature_forge/selectors/recursive.py
feature_forge/utils/__init__.py
feature_forge/utils/report.py
feature_forge/utils/visualizer.py
feature_forge/validators/__init__.py
feature_forge/validators/leak_detector.py
feature_forge/validators/stability.py
featuresmith-0.1.1.dist-info/licenses/LICENSE
featuresmith-0.1.1.dist-info/METADATA
featuresmith-0.1.1.dist-info/WHEEL
featuresmith-0.1.1.dist-info/top_level.txt
featuresmith-0.1.1.dist-info/RECORD
