Metadata-Version: 2.4
Name: featuresmith
Version: 0.1.1
Summary: Intelligent feature engineering and selection for machine learning
Home-page: https://github.com/AbhishekDP2244/feature-forge
Author: AbhishekDP2244
Author-email: AbhishekDP2244 <abhishekpanigrahi.work@gmail.com>
License: MIT
Project-URL: Homepage, https://github.com/AbhishekDP2244/feature-forge
Project-URL: Documentation, https://github.com/AbhishekDP2244/feature-forge#readme
Project-URL: Repository, https://github.com/AbhishekDP2244/feature-forge
Project-URL: Bug Tracker, https://github.com/AbhishekDP2244/feature-forge/issues
Keywords: feature-engineering,machine-learning,kaggle,data-science,feature-selection
Classifier: Development Status :: 3 - Alpha
Classifier: Intended Audience :: Developers
Classifier: Intended Audience :: Science/Research
Classifier: Topic :: Scientific/Engineering :: Artificial Intelligence
Classifier: License :: OSI Approved :: MIT License
Classifier: Programming Language :: Python :: 3
Classifier: Programming Language :: Python :: 3.8
Classifier: Programming Language :: Python :: 3.9
Classifier: Programming Language :: Python :: 3.10
Classifier: Programming Language :: Python :: 3.11
Requires-Python: >=3.8
License-File: LICENSE
Requires-Dist: pandas>=1.3.0
Requires-Dist: numpy>=1.21.0
Requires-Dist: scikit-learn>=1.0.0
Requires-Dist: lightgbm>=3.0.0
Requires-Dist: matplotlib>=3.4.0
Requires-Dist: seaborn>=0.11.0
Requires-Dist: scipy>=1.7.0
Provides-Extra: dev
Requires-Dist: pytest>=7.0.0; extra == "dev"
Requires-Dist: pytest-cov>=4.0.0; extra == "dev"
Requires-Dist: flake8>=6.0.0; extra == "dev"
Requires-Dist: black>=23.0.0; extra == "dev"
Requires-Dist: mypy>=1.0.0; extra == "dev"
Provides-Extra: xgboost
Requires-Dist: xgboost>=1.5.0; extra == "xgboost"
Provides-Extra: catboost
Requires-Dist: catboost>=1.0.0; extra == "catboost"
Provides-Extra: all
Requires-Dist: xgboost>=1.5.0; extra == "all"
Requires-Dist: catboost>=1.0.0; extra == "all"
Dynamic: author
Dynamic: home-page
Dynamic: license-file
Dynamic: requires-python
